luxtelligence_lnoi400_forge/__init__.py
luxtelligence_lnoi400_forge/component.py
luxtelligence_lnoi400_forge/technology.py
luxtelligence_lnoi400_forge/utils.py
luxtelligence_lnoi400_forge-1.4.0.dist-info/licenses/LICENSE
luxtelligence_lnoi400_forge-1.4.0.dist-info/METADATA
luxtelligence_lnoi400_forge-1.4.0.dist-info/WHEEL
luxtelligence_lnoi400_forge-1.4.0.dist-info/top_level.txt
luxtelligence_lnoi400_forge-1.4.0.dist-info/RECORD
