Metadata-Version: 2.4
Name: luxtelligence-lnoi400-forge
Version: 1.4.0
Summary: Luxtelligence LNOI400 PDK implementation for PhotonForge
Author-email: "Flexcompute Inc." <info@flexcompute.com>
Project-URL: homepage, https://github.com/flexcompute/luxtelligence-lnoi400-forge
Project-URL: documentation, https://github.com/flexcompute/luxtelligence-lnoi400-forge
License-File: LICENSE
Requires-Dist: photonforge>=1.2.2
Provides-Extra: test
Requires-Dist: pytest>=7.2; extra == "test"
Dynamic: license-file
